main.py
atomicalsr-0.5.dist-info/METADATA
atomicalsr-0.5.dist-info/WHEEL
atomicalsr-0.5.dist-info/top_level.txt
atomicalsr-0.5.dist-info/RECORD
