Metadata-Version: 2.1
Name: atomicalsr
Version: 0.5
Summary: good for atomicals knowledge
Author-email: nezha <solanaun@gmail.com>
Project-URL: Homepage, https://github.com/Vydha/atomicals
Project-URL: repository, https://github.com/Vydha/atomicals
Project-URL: download, https://github.com/Vydha/atomicals/release
Classifier: Programming Language :: Python :: 3
Classifier: License :: OSI Approved :: MIT License
Classifier: Operating System :: OS Independent
Requires-Python: >=3.8
Requires-Dist: heyreplit ==0.8
